MANIFEST.in
README.rst
setup.py
bin/dlvr
dlvr/__init__.py
dlvr/message.py
dlvr/server.py
dlvr.egg-info/PKG-INFO
dlvr.egg-info/SOURCES.txt
dlvr.egg-info/dependency_links.txt
dlvr.egg-info/not-zip-safe
dlvr.egg-info/top_level.txt