Metadata-Version: 1.0
Name: dlvr
Version: 0.2
Summary: email sending for humans
Home-page: https://github.com/bmaeser/dlvr
Author: Bernhard Maeser
Author-email: bernhard.maeser@gmail.com
License: MIT
Platform: UNKNOWN
Classifier: Development Status :: 5 - Production/Stable
Classifier: Topic :: Utilities
Classifier: Topic :: Communications :: Email
Classifier: Topic :: Communications :: Email :: Email Clients (MUA)
Classifier: Operating System :: POSIX
Classifier: License :: OSI Approved :: MIT License
Classifier: Programming Language :: Python
Classifier: Programming Language :: Python :: 2.6
Classifier: Programming Language :: Python :: 2.7
